{
  "info": {
    "_postman_id": "e0f4d7b8-d7dc-4ca0-8fcb-2519f90d2f1d",
    "name": "Lather E-Commerce Backend APIs",
    "schema": "https://schema.getpostman.com/json/collection/v2.1.0/collection.json",
    "description": "Single Postman collection file. Global prefix `/api/v1`.\n\n**baseUrl:** Set the collection variable `baseUrl` to `http://localhost:<PORT>/api/v1` to match your `.env` `PORT` (default in this file follows repo `.env`).\n\n**Category dropdown:** `GET /categories/dropdown` under **Public (no auth)** — no `Authorization` header; usable by guests and any role.\n\nAdmin: products list + filters, multipart create, paginated categories."
  },
  "item": [
    {
      "name": "Public (no auth)",
      "item": [
        {
          "name": "Category dropdown (no token — any role / guest)",
          "request": {
            "method": "GET",
            "header": [],
            "url": "{{baseUrl}}/categories/dropdown",
            "description": "Do not send Authorization. Response `data`: `[{ id, title }, ...]` (active categories, A→Z). Same for guests, customers, and admins."
          },
          "event": [
            {
              "listen": "test",
              "script": {
                "type": "text/javascript",
                "exec": [
                  "let jsonData = {};",
                  "try { jsonData = pm.response.json(); } catch (e) {}",
                  "const arr = jsonData?.data;",
                  "pm.test('Category dropdown: 200 and data is array', function () {",
                  "  pm.expect(pm.response.code).to.equal(200);",
                  "  pm.expect(arr).to.be.an('array');",
                  "});",
                  "if (arr && arr.length) {",
                  "  pm.test('Each row has id and title', function () {",
                  "    pm.expect(arr[0]).to.have.keys('id', 'title');",
                  "  });",
                  "}"
                ]
              }
            }
          ]
        }
      ]
    },
    {
      "name": "Auth",
      "item": [
        {
          "name": "Register",
          "request": {
            "method": "POST",
            "header": [],
            "body": {
              "mode": "formdata",
              "formdata": [
                { "key": "name", "value": "John Doe", "type": "text" },
                { "key": "email", "value": "john@example.com", "type": "text" },
                { "key": "password", "value": "password123", "type": "text" },
                { "key": "profileImage", "type": "file", "src": "", "disabled": true }
              ]
            },
            "url": "{{baseUrl}}/auth/register"
          },
          "event": [
            {
              "listen": "test",
              "script": {
                "type": "text/javascript",
                "exec": [
                  "let jsonData = {};",
                  "try { jsonData = pm.response.json(); } catch (e) {}",
                  "const token = jsonData?.data?.accessToken || jsonData?.accessToken;",
                  "let role = jsonData?.data?.user?.role;",
                  "if (!role && token) {",
                  "  try {",
                  "    const payload = JSON.parse(atob(token.split('.')[1]));",
                  "    role = payload?.role;",
                  "  } catch (e) {}",
                  "}",
                  "if (token) {",
                  "  const tokenKey = role === 'admin' ? 'admin_token' : 'user_token';",
                  "  pm.collectionVariables.set(tokenKey, token);",
                  "  pm.test('Access token saved from register', function () {",
                  "    pm.expect(token).to.be.a('string').and.not.empty;",
                  "  });",
                  "  pm.test('Token saved by role from register', function () {",
                  "    pm.expect(['admin_token', 'user_token']).to.include(tokenKey);",
                  "  });",
                  "}",
                  "pm.test('Register response is successful', function () {",
                  "  pm.expect(pm.response.code).to.be.oneOf([200, 201]);",
                  "});"
                ]
              }
            }
          ]
        },
        {
          "name": "Login",
          "request": {
            "method": "POST",
            "header": [{ "key": "Content-Type", "value": "application/json" }],
            "body": {
              "mode": "raw",
              "raw": "{\n  \"email\": \"john@example.com\",\n  \"password\": \"password123\"\n}"
            },
            "url": "{{baseUrl}}/auth/login"
          },
          "event": [
            {
              "listen": "test",
              "script": {
                "type": "text/javascript",
                "exec": [
                  "let jsonData = {};",
                  "try { jsonData = pm.response.json(); } catch (e) {}",
                  "const token = jsonData?.data?.accessToken || jsonData?.accessToken;",
                  "let role = jsonData?.data?.user?.role;",
                  "if (!role && token) {",
                  "  try {",
                  "    const payload = JSON.parse(atob(token.split('.')[1]));",
                  "    role = payload?.role;",
                  "  } catch (e) {}",
                  "}",
                  "if (token) {",
                  "  const tokenKey = role === 'admin' ? 'admin_token' : 'user_token';",
                  "  pm.collectionVariables.set(tokenKey, token);",
                  "  pm.test('Access token saved from login', function () {",
                  "    pm.expect(token).to.be.a('string').and.not.empty;",
                  "  });",
                  "  pm.test('Token saved by role from login', function () {",
                  "    pm.expect(['admin_token', 'user_token']).to.include(tokenKey);",
                  "  });",
                  "}",
                  "pm.test('Login response is successful', function () {",
                  "  pm.expect(pm.response.code).to.equal(200);",
                  "});",
                  "const user = jsonData?.data?.user;",
                  "if (user) {",
                  "  pm.test('Login returns user object', function () {",
                  "    pm.expect(user).to.be.an('object');",
                  "    pm.expect(user.email).to.be.a('string');",
                  "  });",
                  "}"
                ]
              }
            }
          ]
        },
        {
          "name": "Forgot Password - Send Token",
          "request": {
            "method": "POST",
            "header": [{ "key": "Content-Type", "value": "application/json" }],
            "body": {
              "mode": "raw",
              "raw": "{\n  \"email\": \"john@example.com\"\n}"
            },
            "url": "{{baseUrl}}/auth/forgot-password/send-token"
          }
        },
        {
          "name": "Forgot Password - Verify Token",
          "request": {
            "method": "POST",
            "header": [{ "key": "Content-Type", "value": "application/json" }],
            "body": {
              "mode": "raw",
              "raw": "{\n  \"email\": \"john@example.com\",\n  \"token\": \"123456\"\n}"
            },
            "url": "{{baseUrl}}/auth/forgot-password/verify-token"
          }
        },
        {
          "name": "Reset Password",
          "request": {
            "method": "POST",
            "header": [{ "key": "Content-Type", "value": "application/json" }],
            "body": {
              "mode": "raw",
              "raw": "{\n  \"email\": \"john@example.com\",\n  \"token\": \"123456\",\n  \"password\": \"newPassword123\"\n}"
            },
            "url": "{{baseUrl}}/auth/reset-password"
          }
        }
      ]
    },
    {
      "name": "Admin",
      "item": [
        {
          "name": "Analytics",
          "item": [
            {
              "name": "Dashboard",
              "request": {
                "method": "GET",
                "header": [{ "key": "Authorization", "value": "Bearer {{admin_token}}" }],
                "url": "{{baseUrl}}/admin/analytics"
              }
            }
          ]
        },
        {
          "name": "Categories",
          "item": [
            {
              "name": "Create Category",
              "request": {
                "method": "POST",
                "header": [
                  { "key": "Authorization", "value": "Bearer {{admin_token}}" },
                  { "key": "Content-Type", "value": "application/json" }
                ],
                "body": {
                  "mode": "raw",
                  "raw": "{\n  \"name\": \"Skincare\",\n  \"description\": \"Skin products\"\n}"
                },
                "url": "{{baseUrl}}/admin/categories"
              },
              "event": [
                {
                  "listen": "test",
                  "script": {
                    "type": "text/javascript",
                    "exec": [
                      "let j = {};",
                      "try { j = pm.response.json(); } catch (e) {}",
                      "const id = j?.data?.id;",
                      "if (id) {",
                      "  pm.collectionVariables.set('categoryId', id);",
                      "  pm.test('categoryId saved from create category', function () {",
                      "    pm.expect(id).to.be.a('string').and.not.empty;",
                      "  });",
                      "}"
                    ]
                  }
                }
              ]
            },
            {
              "name": "List Categories (paginated)",
              "request": {
                "method": "GET",
                "header": [{ "key": "Authorization", "value": "Bearer {{admin_token}}" }],
                "url": "{{baseUrl}}/admin/categories?page=1&limit=10"
              },
              "event": [
                {
                  "listen": "test",
                  "script": {
                    "type": "text/javascript",
                    "exec": [
                      "let jsonData = {};",
                      "try { jsonData = pm.response.json(); } catch (e) {}",
                      "const first = jsonData?.data?.items?.[0];",
                      "if (first?.id) {",
                      "  pm.collectionVariables.set('categoryId', first.id);",
                      "  pm.test('categoryId saved from first row', function () {",
                      "    pm.expect(first.id).to.be.a('string').and.not.empty;",
                      "  });",
                      "}",
                      "pm.test('List categories returns paginated shape', function () {",
                      "  pm.expect(pm.response.code).to.equal(200);",
                      "  pm.expect(jsonData?.data).to.be.an('object');",
                      "  pm.expect(jsonData?.data?.items).to.be.an('array');",
                      "  pm.expect(jsonData?.data?.meta).to.be.an('object');",
                      "});"
                    ]
                  }
                }
              ]
            }
          ]
        },
        {
          "name": "Products",
          "item": [
            {
              "name": "List Products (paginated + filters)",
              "request": {
                "method": "GET",
                "header": [{ "key": "Authorization", "value": "Bearer {{admin_token}}" }],
                "url": {
                  "raw": "{{baseUrl}}/admin/products?page=1&limit=10",
                  "host": ["{{baseUrl}}"],
                  "path": ["admin", "products"],
                  "query": [
                    { "key": "page", "value": "1", "description": "Optional; default 1" },
                    { "key": "limit", "value": "10", "description": "Optional; default 10, max 100" },
                    {
                      "key": "search",
                      "value": "jacket",
                      "disabled": true,
                      "description": "Matches title, legacy name, or category name (substring)"
                    },
                    {
                      "key": "status",
                      "value": "active",
                      "disabled": true,
                      "description": "active | inactive"
                    },
                    {
                      "key": "inventoryStatus",
                      "value": "in-stock",
                      "disabled": true,
                      "description": "in-stock | out-of-stock"
                    },
                    {
                      "key": "fromDate",
                      "value": "2025-01-01",
                      "disabled": true,
                      "description": "createdAt >= start of day UTC"
                    },
                    {
                      "key": "toDate",
                      "value": "2025-12-31",
                      "disabled": true,
                      "description": "createdAt <= end of day UTC"
                    },
                    {
                      "key": "categoryIds[0]",
                      "value": "{{categoryId}}",
                      "disabled": true,
                      "description": "Bracket style; add categoryIds[1], categoryIds[2], … for more ids"
                    },
                    {
                      "key": "categoryIds[1]",
                      "value": "",
                      "disabled": true,
                      "description": "Second category id (optional)"
                    }
                  ]
                },
                "description": "GET /admin/products. Optional filters. categoryIds: use categoryIds[0], categoryIds[1], … or repeat categoryIds / comma-separated / JSON array string."
              },
              "event": [
                {
                  "listen": "test",
                  "script": {
                    "type": "text/javascript",
                    "exec": [
                      "let jsonData = {};",
                      "try { jsonData = pm.response.json(); } catch (e) {}",
                      "const d = jsonData?.data;",
                      "pm.test('List products returns paginated shape', function () {",
                      "  pm.expect(pm.response.code).to.equal(200);",
                      "  pm.expect(d).to.be.an('object');",
                      "  pm.expect(d?.items).to.be.an('array');",
                      "  pm.expect(d?.meta).to.be.an('object');",
                      "  pm.expect(d?.meta?.total).to.be.a('number');",
                      "});"
                    ]
                  }
                }
              ]
            },
            {
              "name": "Create Product (multipart)",
              "request": {
                "method": "POST",
                "header": [{ "key": "Authorization", "value": "Bearer {{admin_token}}" }],
                "body": {
                  "mode": "formdata",
                  "formdata": [
                    {
                      "key": "categoryId",
                      "value": "{{categoryId}}",
                      "type": "text",
                      "description": "Run Admin > List Categories first, or paste a category Mongo id"
                    },
                    { "key": "title", "value": "Summer Jacket", "type": "text" },
                    {
                      "key": "description",
                      "value": "<p>Gentle <strong>HTML</strong> description from editor</p>",
                      "type": "text"
                    },
                    { "key": "inventoryStatus", "value": "in-stock", "type": "text" },
                    { "key": "status", "value": "active", "type": "text" },
                    { "key": "price", "value": "99.99", "type": "text" },
                    { "key": "hasDiscount", "value": "true", "type": "text" },
                    { "key": "discountInPercentage", "value": "10", "type": "text" },
                    {
                      "key": "medias",
                      "description": "Repeat this row to attach multiple images/videos",
                      "type": "file",
                      "src": "",
                      "disabled": true
                    },
                    {
                      "key": "medias",
                      "type": "file",
                      "src": "",
                      "disabled": true
                    }
                  ]
                },
                "url": "{{baseUrl}}/admin/products",
                "description": "Required when hasDiscount is true: discountInPercentage (0–100). Omit medias rows or enable file rows to upload. Response data includes nested category and medias (ProductResource.adminDetail)."
              },
              "event": [
                {
                  "listen": "test",
                  "script": {
                    "type": "text/javascript",
                    "exec": [
                      "let jsonData = {};",
                      "try { jsonData = pm.response.json(); } catch (e) {}",
                      "const id = jsonData?.data?.id;",
                      "if (id) {",
                      "  pm.collectionVariables.set('productId', id);",
                      "  pm.test('productId saved from create', function () {",
                      "    pm.expect(id).to.be.a('string').and.not.empty;",
                      "  });",
                      "}",
                      "pm.test('Create product returns nested category and medias', function () {",
                      "  pm.expect(pm.response.code).to.be.oneOf([200, 201]);",
                      "  pm.expect(jsonData?.data?.category).to.exist;",
                      "  pm.expect(jsonData?.data?.medias).to.be.an('array');",
                      "});"
                    ]
                  }
                }
              ]
            },
            {
              "name": "Get Product Detail",
              "request": {
                "method": "GET",
                "header": [{ "key": "Authorization", "value": "Bearer {{admin_token}}" }],
                "url": "{{baseUrl}}/admin/products/{{productId}}",
                "description": "Same response shape as create/update: nested category + medias. Includes inactive products. Set {{productId}} from create or list."
              }
            },
            {
              "name": "Update Product (multipart)",
              "request": {
                "method": "PATCH",
                "header": [{ "key": "Authorization", "value": "Bearer {{admin_token}}" }],
                "body": {
                  "mode": "formdata",
                  "formdata": [
                    { "key": "title", "value": "Updated title", "type": "text", "disabled": true },
                    { "key": "description", "value": "<p>Updated HTML</p>", "type": "text", "disabled": true },
                    { "key": "price", "value": "89.99", "type": "text", "disabled": true },
                    { "key": "hasDiscount", "value": "false", "type": "text", "disabled": true },
                    {
                      "key": "deleteMediaIds",
                      "value": "[\"paste-media-object-id-here\"]",
                      "type": "text",
                      "disabled": true,
                      "description": "JSON array or use deleteMediaIds[0]=id style — only ids already on this product"
                    },
                    {
                      "key": "medias",
                      "type": "file",
                      "src": "",
                      "disabled": true,
                      "description": "Append new images/videos"
                    }
                  ]
                },
                "url": "{{baseUrl}}/admin/products/{{productId}}",
                "description": "All parts optional. Enable fields to patch. Response same shape as create (category + medias). Remove Content-Type header so Postman sets multipart boundary."
              }
            },
            {
              "name": "Delete Product",
              "request": {
                "method": "DELETE",
                "header": [{ "key": "Authorization", "value": "Bearer {{admin_token}}" }],
                "url": "{{baseUrl}}/admin/products/{{productId}}"
              }
            }
          ]
        },
        {
          "name": "Orders",
          "item": [
            {
              "name": "List Orders (Paginated + Filters)",
              "request": {
                "method": "GET",
                "header": [{ "key": "Authorization", "value": "Bearer {{admin_token}}" }],
                "url": "{{baseUrl}}/admin/orders?page=1&limit=10&search=&status=&fromDate=&toDate=&paymentStatus=&userId=",
                "description": "Paginated admin orders with optional filters. Empty query values are ignored by backend. Search matches user name/email, product title/name, and category name. Each row includes items, user, and paymentLog."
              }
            },
            {
              "name": "Get Order By Id",
              "request": {
                "method": "GET",
                "header": [{ "key": "Authorization", "value": "Bearer {{admin_token}}" }],
                "url": "{{baseUrl}}/admin/orders/{{orderId}}",
                "description": "Admin detail response with OrderResource.adminOne shape: items with product/category/medias, embedded user, and paymentLog."
              }
            },
            {
              "name": "Patch Order (Status + Reason)",
              "request": {
                "method": "PATCH",
                "header": [
                  { "key": "Authorization", "value": "Bearer {{admin_token}}" },
                  { "key": "Content-Type", "value": "application/json" }
                ],
                "body": {
                  "mode": "raw",
                  "raw": "{\n  \"status\": \"processing\",\n  \"reason\": \"Required only when status is cancelled or rejected\"\n}"
                },
                "url": "{{baseUrl}}/admin/orders/{{orderId}}",
                "description": "PATCH order status. Provide reason when status is cancelled or rejected."
              }
            },
            {
              "name": "Mark Order Payment Paid",
              "request": {
                "method": "PATCH",
                "header": [
                  { "key": "Authorization", "value": "Bearer {{admin_token}}" },
                  { "key": "Content-Type", "value": "application/json" }
                ],
                "body": {
                  "mode": "raw",
                  "raw": "{\n  \"transactionId\": \"txn_1234567890\"\n}"
                },
                "url": "{{baseUrl}}/admin/orders/{{orderId}}/payment/paid"
              }
            }
          ]
        }
      ]
    },
    {
      "name": "User",
      "item": [
        {
          "name": "Products",
          "item": [
            {
              "name": "List Products",
              "request": {
                "method": "GET",
                "url": "{{baseUrl}}/products?gender=unisex&category=Skincare&size=M&color=Black&price=low_to_high&sort=desc",
                "description": "GET /api/v1/products. Each item includes populated category and medias (id, path, mimeType, kind, …) like the product detail response."
              }
            },
            {
              "name": "Latest Products",
              "request": {
                "method": "GET",
                "url": "{{baseUrl}}/products/latest"
              }
            },
            {
              "name": "Sale Products",
              "request": {
                "method": "GET",
                "url": "{{baseUrl}}/products/sale"
              }
            },
            {
              "name": "Popular Products",
              "request": {
                "method": "GET",
                "url": "{{baseUrl}}/products/popular"
              }
            },
            {
              "name": "Get Product Detail",
              "request": {
                "method": "GET",
                "url": "{{baseUrl}}/products/{{productId}}",
                "description": "Storefront product page payload (category + medias). Inactive products return 404. Set {{productId}} from Admin create or paste an id."
              }
            }
          ]
        },
        {
          "name": "Categories",
          "item": [
            {
              "name": "List Categories",
              "request": {
                "method": "GET",
                "url": "{{baseUrl}}/categories"
              }
            }
          ]
        },
        {
          "name": "Cart",
          "item": [
            {
              "name": "Get Cart",
              "request": {
                "method": "GET",
                "header": [
                  { "key": "Authorization", "value": "Bearer {{user_token}}" },
                  { "key": "sessionId", "value": "{{sessionId}}" }
                ],
                "url": "{{baseUrl}}/cart",
                "description": "data: parent cart (cartableType user, cartableId = user id or sessionId) and items[] (cartableType cart, cartableId = parent cart id). Each item includes product with medias."
              }
            },
            {
              "name": "Add Or Update Cart Item",
              "request": {
                "method": "POST",
                "header": [
                  { "key": "Authorization", "value": "Bearer {{user_token}}" },
                  { "key": "sessionId", "value": "{{sessionId}}" },
                  { "key": "Content-Type", "value": "application/json" }
                ],
                "body": {
                  "mode": "raw",
                  "raw": "{\n  \"productId\": \"{{productId}}\",\n  \"quantity\": 2,\n  \"size\": \"M\",\n  \"color\": \"Black\",\n  \"discount\": 10\n}"
                },
                "url": "{{baseUrl}}/cart/items",
                "description": "Creates user cart row if needed, then upserts line by productId+size+color. Omit size/color for default variant. discount 0-100 optional (else product discount snapshotted when hasDiscount)."
              }
            },
            {
              "name": "Remove Cart Item",
              "request": {
                "method": "DELETE",
                "header": [
                  { "key": "Authorization", "value": "Bearer {{user_token}}" },
                  { "key": "sessionId", "value": "{{sessionId}}" }
                ],
                "url": "{{baseUrl}}/cart/items/{{productId}}"
              }
            }
          ]
        },
        {
          "name": "Orders",
          "item": [
            {
              "name": "Place Order",
              "request": {
                "method": "POST",
                "header": [
                  { "key": "Authorization", "value": "Bearer {{user_token}}" },
                  { "key": "sessionId", "value": "{{sessionId}}" },
                  { "key": "Content-Type", "value": "application/json" }
                ],
                "body": {
                  "mode": "raw",
                  "raw": "{\n  \"paymentMethod\": \"cod\",\n  \"contactInfo\": {\n    \"fullName\": \"John Doe\",\n    \"phone\": \"+923001234567\",\n    \"email\": \"john@example.com\",\n    \"addressLine1\": \"Street 12, House 44\",\n    \"addressLine2\": \"Near central park\",\n    \"city\": \"Karachi\",\n    \"state\": \"Sindh\",\n    \"country\": \"Pakistan\",\n    \"postalCode\": \"74200\"\n  },\n  \"shippingAddress\": {\n    \"fullName\": \"John Doe\",\n    \"phone\": \"+923001234567\",\n    \"email\": \"john@example.com\",\n    \"addressLine1\": \"Street 12, House 44\",\n    \"addressLine2\": \"Near central park\",\n    \"city\": \"Karachi\",\n    \"state\": \"Sindh\",\n    \"country\": \"Pakistan\",\n    \"postalCode\": \"74200\"\n  },\n  \"billingAddress\": {\n    \"fullName\": \"John Doe\",\n    \"phone\": \"+923001234567\",\n    \"email\": \"john@example.com\",\n    \"addressLine1\": \"Street 12, House 44\",\n    \"addressLine2\": \"Near central park\",\n    \"city\": \"Karachi\",\n    \"state\": \"Sindh\",\n    \"country\": \"Pakistan\",\n    \"postalCode\": \"74200\"\n  }\n}"
                },
                "url": "{{baseUrl}}/orders",
                "description": "Creates Order header, then OrderItem rows (`orderItems` collection), then addresses + payment log, clears cart. Response `data` includes order totals plus `items[]` (each: orderId, productId, quantity, unitPrice). Ensure cart has lines before calling."
              }
            },
            {
              "name": "List Orders",
              "request": {
                "method": "GET",
                "header": [
                  { "key": "Authorization", "value": "Bearer {{user_token}}" },
                  { "key": "sessionId", "value": "{{sessionId}}" }
                ],
                "url": "{{baseUrl}}/orders?page=1&limit=10&search=&status=&paymentStatus=&fromDate=&toDate=",
                "description": "Paginated orders for the current owner. Logged-in users are filtered by `userId` from JWT; guests are filtered by `sessionId` header. Empty query values are ignored. Search matches product title/name or category name. Response: { items: OrderResource[], meta }."
              }
            },
            {
              "name": "Get Order By Id",
              "request": {
                "method": "GET",
                "header": [
                  { "key": "Authorization", "value": "Bearer {{user_token}}" },
                  { "key": "sessionId", "value": "{{sessionId}}" }
                ],
                "url": "{{baseUrl}}/orders/{{orderId}}",
                "description": "Same OrderResource shape; each `items[]` entry includes `product` with `medias` (loaded like storefront). Owner-only."
              }
            }
          ]
        },
        {
          "name": "Addresses",
          "item": [
            {
              "name": "Create Address",
              "request": {
                "method": "POST",
                "header": [
                  { "key": "Authorization", "value": "Bearer {{user_token}}" },
                  { "key": "Content-Type", "value": "application/json" }
                ],
                "body": {
                  "mode": "raw",
                  "raw": "{\n  \"type\": \"shipping\",\n  \"fullName\": \"John Doe\",\n  \"phone\": \"+923001234567\",\n  \"email\": \"john@example.com\",\n  \"addressLine1\": \"Street 12, House 44\",\n  \"addressLine2\": \"Near central park\",\n  \"city\": \"Karachi\",\n  \"state\": \"Sindh\",\n  \"country\": \"Pakistan\",\n  \"postalCode\": \"74200\"\n}"
                },
                "url": "{{baseUrl}}/addresses"
              }
            },
            {
              "name": "List Addresses",
              "request": {
                "method": "GET",
                "header": [{ "key": "Authorization", "value": "Bearer {{user_token}}" }],
                "url": "{{baseUrl}}/addresses"
              }
            }
          ]
        },
        {
          "name": "Profile",
          "item": [
            {
              "name": "My Profile",
              "request": {
                "method": "GET",
                "header": [{ "key": "Authorization", "value": "Bearer {{user_token}}" }],
                "url": "{{baseUrl}}/users/me"
              }
            }
          ]
        }
      ]
    }
  ],
  "variable": [
    {
      "key": "baseUrl",
      "value": "http://localhost:3000/api/v1",
      "description": "Sync with .env PORT: http://localhost:<PORT>/api/v1 — default 3000 from repo .env"
    },
    {
      "key": "admin_token",
      "value": ""
    },
    {
      "key": "user_token",
      "value": ""
    },
    {
      "key": "categoryId",
      "value": "",
      "description": "Filled by Admin > List Categories test, or paste manually before Create Product"
    },
    {
      "key": "productId",
      "value": ""
    },
    {
      "key": "orderId",
      "value": ""
    },
    {
      "key": "sessionId",
      "value": ""
    }
  ]
}
